LICENSE.txt
README.md
setup.cfg
setup.py
life4safe_commons.egg-info/PKG-INFO
life4safe_commons.egg-info/SOURCES.txt
life4safe_commons.egg-info/dependency_links.txt
life4safe_commons.egg-info/top_level.txt
live4safe_commons/__init__.py
live4safe_commons/cloud_storage.py
live4safe_commons/connection.py
live4safe_commons/controller.py
live4safe_commons/liveness_status_enum.py
live4safe_commons/logger_app.py
live4safe_commons/misc.py
live4safe_commons/server_instance.py